voxa/__init__.py
voxa/main.py
voxa-0.0.2.dist-info/METADATA
voxa-0.0.2.dist-info/WHEEL
voxa-0.0.2.dist-info/top_level.txt
voxa-0.0.2.dist-info/RECORD
