Metadata-Version: 2.1
Name: voxa
Version: 0.0.2
Summary: The Voxa Language Translation Service
Author: Dark25 (Ruben Roy)
Author-email: me@ruben-roy.com
Keywords: python,translate,language,free,translation
Classifier: Development Status :: 3 - Alpha
Classifier: Intended Audience :: Developers
Classifier: License :: OSI Approved :: MIT License
Classifier: Programming Language :: Python :: 3
Classifier: Programming Language :: Python :: 3.6
Classifier: Programming Language :: Python :: 3.7
Classifier: Programming Language :: Python :: 3.8
Classifier: Programming Language :: Python :: 3.9
Requires-Dist: requests
